ansiblecall/__init__.py
ansiblecall/_version.py
ansiblecall/utils/__init__.py
ansiblecall/utils/cache.py
ansiblecall/utils/config.py
ansiblecall/utils/ctx.py
ansiblecall/utils/loader.py
ansiblecall/utils/respawn.py
ansiblecall/utils/rt.py
ansiblecall/utils/typefactory.py
ansiblecall-0.3.5.dist-info/METADATA
ansiblecall-0.3.5.dist-info/WHEEL
ansiblecall-0.3.5.dist-info/licenses/LICENSE
ansiblecall-0.3.5.dist-info/RECORD
