Metadata-Version: 2.4
Name: ansiblecall
Version: 0.3.5
Summary: Call ansible modules with python script
Project-URL: Documentation, https://github.com/cheburakshu/ansible-call#readme
Project-URL: Issues, https://github.com/cheburakshu/ansible-call/issues
Project-URL: Source, https://github.com/cheburakshu/ansible-call
Author-email: cheburakshu <cheburakshu@gmail.com>
License-Expression: GPL-3.0-or-later
License-File: LICENSE
Classifier: Development Status :: 4 - Beta
Classifier: Programming Language :: Python
Classifier: Programming Language :: Python :: 3.10
Classifier: Programming Language :: Python :: 3.11
Classifier: Programming Language :: Python :: 3.12
Classifier: Programming Language :: Python :: Implementation :: CPython
Classifier: Programming Language :: Python :: Implementation :: PyPy
Requires-Python: >=3.10
Requires-Dist: ansible
